azrailv3/__init__.py
azrailv3/bypass.py
azrailv3-0.1.dist-info/METADATA
azrailv3-0.1.dist-info/WHEEL
azrailv3-0.1.dist-info/top_level.txt
azrailv3-0.1.dist-info/RECORD
