Metadata-Version: 2.1
Name: azrailv3
Version: 0.1
Summary: A module to bypass reCAPTCHA v3 challenges.
Home-page: https://github.com/yourusername/azrailv3
Author: Fatih
Author-email: your.email@example.com
Classifier: Programming Language :: Python :: 3
Classifier: License :: OSI Approved :: MIT License
Classifier: Operating System :: OS Independent
Requires-Dist: requests
